<?xml version="1.0" encoding="UTF-8"?>
<!DOCTYPE CLISH_MODULE [
<!ENTITY START_PORT_ID "1">
<!ENTITY MAX_PORT_ID "32">
<!ENTITY START_SUB_PORT_ID "1">
<!ENTITY MAX_SUB_PORT_ID "4">
<!ENTITY MAX_MTU "9216">
]>
<CLISH_MODULE xmlns="http://www.dellemc.com/sonic/XMLSchema" xmlns:xsi="http://www.w3.org/2001/XMLSchema-instance" xmlns:xi="http://www.w3.org/2001/XInclude" xsi:schemaLocation="http://www.dellemc.com/sonic/XMLSchema http://www.dellemc.com/sonic/XMLSchema/clish.xsd">
   <VIEW name="enable-view">
   <COMMAND
        name="show threshold"
        help="show threshold commands"/>
   <COMMAND
	name="show threshold breaches"
	help="Show threshold breach entries"
	ptype="SUBCOMMAND"
	mode="subcommand">
	<ACTION builtin="clish_pyobj">sonic_cli_threshold get_threshold_breach_event_reports ${__full_line}&#xA; </ACTION>
	<DOCGEN>
           <DESCRIPTION>
                   This command is used to show information about threshold breach events recorded by the system.
           </DESCRIPTION>
           <USAGE>
                   Use this command to display the threshold breach events recorded by the system.
           </USAGE>
           <EXAMPLE
		    summary="Show threshold breaches">
	------------------------------------------------------------------------------------------------------------------
	Event-id    Buffer            Type        Port           Index     Breach Value(%)       Time-stamp
	------------------------------------------------------------------------------------------------------------------
	2           priority-group    shared      Ethernet0      7         77                    2020-04-14-11:35:20
	3           queue             unicast     Ethernet0      5         45                    2020-04-17-11:30:20
	   </EXAMPLE>
	</DOCGEN>
    </COMMAND>
    <COMMAND name="show threshold buffer-pool" help="Show buffer-pool configuration" ptype="SUBCOMMAND" mode="subcommand">
      <ACTION builtin="clish_pyobj">sonic_cli_threshold get_list_sonic_threshold_sonic_threshold_threshold_bufferpool_table_threshold_bufferpool_table_list ${__full_line}</ACTION>
    </COMMAND>
    <COMMAND name="show threshold priority-group" help="Show priority-group threshold configuration" ptype="SUBCOMMAND" mode="subcommand">
      <PARAM name="threshold_buffer_type" help="choose from shared, headroom." mode="switch" ptype="SUBCOMMAND">
        <PARAM name="headroom" help="choose headroom as threshold buffer type" ptype="SUBCOMMAND" mode="subcommand"> </PARAM>
        <PARAM name="shared" help="choose shared as threshold buffer type" ptype="SUBCOMMAND" mode="subcommand"> </PARAM>
      </PARAM>
      <ACTION builtin="clish_pyobj">sonic_cli_threshold get_list_sonic_threshold_sonic_threshold_threshold_table_threshold_table_list ${__full_line}</ACTION>
    </COMMAND>
    <COMMAND name="show threshold queue" help="Show queue threshold configuration" ptype="SUBCOMMAND" mode="subcommand">
      <PARAM name="queue_buffer_type" help="choose from unicast/multicast as queue buffer type" mode="switch" ptype="SUBCOMMAND">
        <PARAM name="CPU" help="choose threshold cpu queue" ptype="SUBCOMMAND" mode="subcommand"> </PARAM>
        <PARAM name="multicast" help="choose multicast as queue_buffer_type" ptype="SUBCOMMAND" mode="subcommand"> </PARAM>
        <PARAM name="unicast" help="choose unicast as queue_buffer_type" ptype="SUBCOMMAND" mode="subcommand"> </PARAM>
      </PARAM>
      <ACTION builtin="clish_pyobj">sonic_cli_threshold get_list_sonic_threshold_sonic_threshold_threshold_table_threshold_table_list ${__full_line}</ACTION>
    </COMMAND>
    <COMMAND name="clear threshold"
                 help="Clear threshold"
                 ptype="SUBCOMMAND"
                 >
                 <PARAM name="breach"
                        help="Clear threshold breach events"
                        ptype="SUBCOMMAND"
                        mode="subcommand"
                        >
                        <PARAM
                            name="eventid-switch"
                            help="breach clear type all or eventId"
                            ptype="SUBCOMMAND"
                            mode="switch"
                            >
                            <PARAM
                                name="all"
                                help="Clear all threshold breaches"
                                ptype="SUBCOMMAND"
                                mode="subcommand"
                                >
                            </PARAM>
                            <PARAM name="eventId"
                                   help="Clear threshold breach of an eventId"
                                   ptype="RANGE_0_65535">
                            </PARAM>
                            </PARAM>
                            </PARAM>
			<ACTION builtin="clish_pyobj">sonic_cli_threshold rpc_sonic_threshold_clear_threshold_breach ${__full_line} </ACTION>
			<DOCGEN>
			<DESCRIPTION>
				This command is used to clear all or a given threshold breach event(s) recorded by the system.
			</DESCRIPTION>
			<USAGE>
				Use this command to clear all or a given threshold breach event(s) recorded by the system.
			</USAGE>
			<EXAMPLE
				summary="Clear threshold breach">
					sonic-cli# clear threshold breach all
					sonic-cli# clear threshold breach eventId
			</EXAMPLE>
			</DOCGEN>
	</COMMAND>
   </VIEW>

   <VIEW
       name="configure-view"
       >
     <COMMAND name="threshold" help="Configure threshold for buffer pool."/>
	<COMMAND name="threshold buffer-pool" help="Configure buffer pool threshold."
		ptype="SUBCOMMAND"
		mode="subcommand"
		command_tables="sonic-threshold:sonic-threshold/THRESHOLD_BUFFERPOOL_TABLE/THRESHOLD_BUFFERPOOL_TABLE_LIST/pool_name"
		>
                <PARAM
                    name="buffer_pool_name"
                    help="configure buffer pool name"
                    ptype="STRING_63"
		    dbpath="sonic-threshold:sonic-threshold/THRESHOLD_BUFFERPOOL_TABLE/THRESHOLD_BUFFERPOOL_TABLE_LIST/pool_name"
                    >
                 </PARAM>
		<PARAM
                       name="threshold_value"
                       help="threshold value"
                       ptype="PERCENT_1"
		       dbpath="sonic-threshold:sonic-threshold/THRESHOLD_BUFFERPOOL_TABLE/THRESHOLD_BUFFERPOOL_TABLE_LIST/threshold"
		       >
                </PARAM>
	<ACTION builtin="clish_pyobj">sonic_cli_threshold patch_sonic_threshold_sonic_threshold_threshold_bufferpool_table_threshold_bufferpool_table_list_threshold ${__params}</ACTION>
	<DOCGEN>
           <DESCRIPTION>
                   this command is to configure buffer pool threshold on ingress/egress buffers pools-lossy/lossless.
           </DESCRIPTION>
           <USAGE>
                   use this command to configure buffer pool threshold on ingress/egress buffer pools-lossy/lossless.
           </USAGE>
           <EXAMPLE
                    summary="buffer pool threshold configuration commands.">
			    sonic(config)# threshold buffer-pool ingress_lossless_pool 1
			    sonic(config)# threshold buffer-pool egress_lossy_pool 1
			    sonic(config)# threshold buffer-pool egress_lossless_pool 1
           </EXAMPLE>
	</DOCGEN>
         </COMMAND>
     <!-- no buffer-pool commands -->
     <COMMAND
         name="no threshold"
         help="Remove threshold configured for buffer-pool"
         />
     <COMMAND name="no threshold buffer-pool"
             help="Remove buffer-pool threshold config"
             ptype="SUBCOMMAND"
             mode="subcommand">
                <ACTION builtin="clish_pyobj">sonic_cli_threshold delete_list_sonic_threshold_sonic_threshold_threshold_bufferpool_table_threshold_bufferpool_table_list ${__full_line}</ACTION>
                <DOCGEN>
                <DESCRIPTION>
                        This command can be used to remove buffer-pool threshold configured on ingress and egress buffers.
                </DESCRIPTION>
                <USAGE>
                        Use this command to remove buffer-pool threshold configured on ingress and egress buffers.
                </USAGE>
                <EXAMPLE
			summary="Removes previously configured buffer-pool threshold on ingress and egress buffers.">
                                sonic(config)# no threshold buffer-pool
                </EXAMPLE>
                </DOCGEN>
     </COMMAND>
     </VIEW>

     <VIEW name="configure-if-view">
	<COMMAND name="threshold" help="Configure priority-group/queue threshold on an interface."/>
	<COMMAND name="threshold priority-group"
		 help="Configure priority-group thresholds" ptype="SUBCOMMAND" mode="subcommand" command_tables="sonic-threshold:sonic-threshold/THRESHOLD_TABLE/THRESHOLD_TABLE_LIST/buffer={buffer},threshold_buffer_type={threshold},interface_name={name},buffer_index_per_port={port}" dbpath="sonic-threshold:sonic-threshold/THRESHOLD_TABLE/THRESHOLD_TABLE_LIST/buffer=priority-group">
		<PARAM name="PG-Index"
			help="PG Index value"
			ptype="RANGE_0_7"
      dbpath="sonic-threshold:sonic-threshold/THRESHOLD_TABLE/THRESHOLD_TABLE_LIST/buffer_index_per_port">
		</PARAM>
		<PARAM
			name="threshold_buffer_type"
			help="choose from shared, headroom."
			mode="switch"
			ptype="SUBCOMMAND">
                <PARAM
                       name="headroom"
                       help="choose headroom as threshold buffer type"
                       ptype="SUBCOMMAND"
                       mode="subcommand"
                       dbpath="sonic-threshold:sonic-threshold/THRESHOLD_TABLE/THRESHOLD_TABLE_LIST/threshold_buffer_type=headroom">
		</PARAM>
		<PARAM
                       name="shared"
                       help="choose shared as threshold buffer type"
                       ptype="SUBCOMMAND"
                       mode="subcommand"
                       dbpath="sonic-threshold:sonic-threshold/THRESHOLD_TABLE/THRESHOLD_TABLE_LIST/threshold_buffer_type=shared">
		</PARAM>
		</PARAM>
		<PARAM
		       name="threshold_value"
		       help="Threshold value"
		       ptype="PERCENT_1"
           dbpath="sonic-threshold:sonic-threshold/THRESHOLD_TABLE/THRESHOLD_TABLE_LIST/threshold">
                </PARAM>
	    <ACTION builtin="clish_pyobj">sonic_cli_threshold patch_sonic_threshold_sonic_threshold_threshold_table_threshold_table_list_threshold ${__full_line} ${iface}</ACTION>
		<DOCGEN>
		<DESCRIPTION>
			This command is used to configure a threshold for a specific priority-group shared/headroom buffer of an interface. The threshold value is provided in %. Valid values are 1-100.
		</DESCRIPTION>
		<USAGE>
			Use this command to configure a threshold for a  specific priority-group shared/headroom buffer of an interface.
		</USAGE>
		<EXAMPLE summary="Configure priority-group buffer threshold configuration.">
				sonic(conf-if-Ethernet0)# threshold priority-group 5 headroom 57
				sonic(conf-if-Ethernet0)# threshold priority-group 7 shared 78
		</EXAMPLE>
		</DOCGEN>
	</COMMAND>
	<COMMAND name="threshold queue"
		 help="Configure queue thresholds" ptype="SUBCOMMAND" mode="subcommand" command_tables="sonic-threshold:sonic-threshold/THRESHOLD_TABLE/THRESHOLD_TABLE_LIST/buffer={buffer}, threshold_buffer_type={threshold},interface_name={name},buffer_index_per_port={port}" dbpath="sonic-threshold:sonic-threshold/THRESHOLD_TABLE/THRESHOLD_TABLE_LIST/buffer=queue">
		<PARAM
                       name="queue_index"
                       help="queue_index value"
                       ptype="RANGE_0_7"
                       dbpath="sonic-threshold:sonic-threshold/THRESHOLD_TABLE/THRESHOLD_TABLE_LIST/buffer_index_per_port">
                </PARAM>
	        <PARAM
			name="queue_buffer_type"
			help="choose from unicast/multicast as queue buffer type"
			mode="switch"
			ptype="SUBCOMMAND">
		<PARAM
			name="unicast"
			help="choose unicast as queue_buffer_type"
			ptype="SUBCOMMAND"
			mode="subcommand"
      dbpath="sonic-threshold:sonic-threshold/THRESHOLD_TABLE/THRESHOLD_TABLE_LIST/threshold_buffer_type=unicast">
		</PARAM>
		<PARAM
                       name="multicast"
                       help="choose multicast as queue_buffer_type"
                       ptype="SUBCOMMAND"
                       mode="subcommand"
                       dbpath="sonic-threshold:sonic-threshold/THRESHOLD_TABLE/THRESHOLD_TABLE_LIST/threshold_buffer_type=multicast">
		</PARAM>
                </PARAM>
		<PARAM
		       name="threshold_value"
		       help="Threshold value"
		       ptype="PERCENT_1"
           dbpath="sonic-threshold:sonic-threshold/THRESHOLD_TABLE/THRESHOLD_TABLE_LIST/threshold">
                </PARAM>
		<ACTION builtin="clish_pyobj">sonic_cli_threshold patch_sonic_threshold_sonic_threshold_threshold_table_threshold_table_list_threshold ${__full_line} ${iface} </ACTION>
		<DOCGEN>
		<DESCRIPTION>
			This command is used to configure a threshold for a specific unicast/multicast queue of an interface. The threshold value is provided in %. Valid values are 1-100..
		</DESCRIPTION>
		<USAGE>
			Use this command to configure queue threshold for a specific unicast/multicast queue of an interface.
		</USAGE>
		<EXAMPLE summary="Configure queue buffer threshold configuration.">
					sonic(conf-if-Ethernet0)# threshold queue 4 unicast 47
					sonic(conf-if-Ethernet0)# threshold queue 2 multicast 67
		</EXAMPLE>
		</DOCGEN>
	</COMMAND>
	<COMMAND
	        name="no threshold"
		help="Remove priority-group/queue thresholds"
		>
	</COMMAND>

	<!-- no threshold priority-group -->
	<COMMAND name="no threshold priority-group"
		help="Clears priority-group buffer threshold."
		ptype="SUBCOMMAND"
		mode="subcommand">
                <PARAM name="PG-Index" help="PG Index value" ptype="RANGE_0_7"> </PARAM>
                <PARAM name="clear-priority-group-subcommands" help="Clear priority group sub commands" mode="switch" ptype="SUBCOMMAND">
		<PARAM name="headroom" help="Choose headroom as threshold buffer type." ptype="SUBCOMMAND" mode="subcommand"> </PARAM>
		<PARAM name="shared" help="Choose shared as threshold buffer type." ptype="SUBCOMMAND" mode="subcommand"> </PARAM>
                </PARAM>
	<ACTION builtin="clish_pyobj">sonic_cli_threshold delete_sonic_threshold_sonic_threshold_threshold_table_threshold_table_list_threshold ${__full_line} ${iface}</ACTION>
		<DOCGEN>
		<DESCRIPTION>
			This command can be used to clear a previously configured threshold on shared/headroom priority-group buffer of an interface.
		</DESCRIPTION>
		<USAGE>
			Use this command to clear a previously configured threshold on shared/headroom priority-group buffer of an interface.
		</USAGE>
		<EXAMPLE summary="Clear a previously configured threshold on shared/headroom priority-group buffer of an interface.">
				 sonic(conf-if-Ethernet0)# no threshold priority-group 5 headroom
				 sonic(conf-if-Ethernet0)# no threshold priority-group 7 shared
			</EXAMPLE>
		</DOCGEN>
	</COMMAND>
	<!-- no threshold queue -->
	<COMMAND name="no threshold queue"
             help="Clears queue buffer threshold."
             ptype="SUBCOMMAND"
             mode="subcommand">
		<PARAM name="queue_index" help="queue Index value" ptype="RANGE_0_7"> </PARAM>
		<PARAM name="clear-queue-subcommands" help="Clear queue sub commands" mode="switch" ptype="SUBCOMMAND">
		<PARAM name="unicast" help="Choose unicast as queue buffer type." ptype="SUBCOMMAND" mode="subcommand"> </PARAM>
		<PARAM name="multicast" help="Choose multicast as queue buffer type." ptype="SUBCOMMAND" mode="subcommand"> </PARAM>
		</PARAM>
	        <ACTION builtin="clish_pyobj">sonic_cli_threshold delete_sonic_threshold_sonic_threshold_threshold_table_threshold_table_list_threshold ${__full_line} ${iface} </ACTION>
		<DOCGEN>
		<DESCRIPTION>
			This command can be used to clear a previously configured threshold on unicast/multicast queue buffer of an interface .
		</DESCRIPTION>
		<USAGE>
			Use this command to clear a previously configured threshold on unicast/multicast queue buffer of an interface.
		</USAGE>
		<EXAMPLE summary="Clear a previously configured threshold on unicast/multicast queue buffer of an interface.">
				sonic(conf-if-Ethernet0)# no threshold queue 7 unicast
				sonic(conf-if-Ethernet0)# no threshold queue 5 multicast
			</EXAMPLE>
		</DOCGEN>
    </COMMAND>
    </VIEW>

    <VIEW name="config-if-CPU-view">
        <COMMAND name="threshold" help="Configure threshold on CPU interface."/>
        <COMMAND
	     name="threshold queue"
	     help="Configure queue buffer threshold on CPU interface."
	     ptype="SUBCOMMAND"
       mode="subcommand"
       dbpath="sonic-threshold:sonic-threshold/THRESHOLD_TABLE/THRESHOLD_TABLE_LIST/buffer=queue">
		    <PARAM
                       name="cpu_queue_index"
                       help="cpu_queue_index value"
                       ptype="RANGE_0_47"
                       dbpath="sonic-threshold:sonic-threshold/THRESHOLD_TABLE/THRESHOLD_TABLE_LIST/buffer_index_per_port">
                </PARAM>
		            <PARAM
                       name="multicast"
                       help="choose multicast as queue buffer type on CPU interface"
                       ptype="SUBCOMMAND"
                       mode="subcommand"
                       dbpath="sonic-threshold:sonic-threshold/THRESHOLD_TABLE/THRESHOLD_TABLE_LIST/threshold_buffer_type=multicast">
                </PARAM>
		<PARAM
		       name="threshold_value"
		       help="Threshold value"
		       ptype="PERCENT_1"
           dbpath="sonic-threshold:sonic-threshold/THRESHOLD_TABLE/THRESHOLD_TABLE_LIST/threshold">
                </PARAM>
		<ACTION builtin="clish_pyobj">sonic_cli_threshold patch_sonic_threshold_sonic_threshold_threshold_table_threshold_table_list_threshold ${__full_line}  ${cpu_ifname}</ACTION>
		<DOCGEN>
		<DESCRIPTION>
			This command is used to configure multicact queue buffer threshold of CPU interface. The threshold value is provided in %. Valid values are 1-100..
		</DESCRIPTION>
		<USAGE>
			Use this command to configure multicast queue buffer threshold of CPU interface.
		</USAGE>
		<EXAMPLE summary="Configure queue buffer threshold of CPU interface.">
			sonic(conf-if-CPU)# threshold queue 3 multicast 37
		</EXAMPLE>
		</DOCGEN>
	</COMMAND>

        <COMMAND
            name="no"
            help="Negate a command or set its defaults"
            />
	<COMMAND
	        name="no threshold"
		help="Remove CPU interface thresholds"
                ptype="SUBCOMMAND"
                mode="subcommand">
	</COMMAND>
	<COMMAND name="no threshold queue"
		help="Clears CPU interface queue buffer threshold."
		ptype="SUBCOMMAND"
		mode="subcommand">
		<PARAM name="cpu_queue_index" help="cpu_queue index value" ptype="RANGE_0_47"> </PARAM>
		<PARAM name="clear-queue-subcommands" help="Clear queue sub commands" mode="switch" ptype="SUBCOMMAND">
		<PARAM name="multicast" help="Choose multicast as queue buffer type." ptype="SUBCOMMAND" mode="subcommand"> </PARAM>
		</PARAM>
		<ACTION builtin="clish_pyobj">sonic_cli_threshold delete_sonic_threshold_sonic_threshold_threshold_table_threshold_table_list_threshold ${__full_line} ${cpu_ifname} </ACTION>
		<DOCGEN>
		<DESCRIPTION>
			This command can be used to clear a previously configured threshold on multicast queue buffer of CPU interface.
		</DESCRIPTION>
		<USAGE>
			Use this command to clear a previously configured threshold on multicast queue buffer of CPU interface.
		</USAGE>
		<EXAMPLE summary="Clears previously configured threshold on multicast queue buffer of CPU interface.">
				sonic(conf-if-CPU)# no threshold queue 7 multicast 77
		</EXAMPLE>
		</DOCGEN>
	</COMMAND>
</VIEW>
</CLISH_MODULE>
